{
  "name": "ctmobile",
  "version": "2.0.0",
  "description": "一个移动端框架",
  "main": "dist/ctmobile.js",
  "scripts": {
    "test": "echo \"Error: no test specified\" && exit 1",
    "build": "cross-env webpack --config webpack.config.js"
  },
  "author": "playerljc",
  "license": "ISC",
  "devDependencies": {
    "@babel/core": "^7.1.2",
    "@babel/plugin-transform-runtime": "^7.1.0",
    "@babel/preset-env": "^7.1.0",
    "@babel/runtime": "^7.1.2",
    "babel-eslint": "^10.0.1",
    "babel-loader": "^8.0.4",
    "babel-preset-env": "^1.7.0",
    "copy-webpack-plugin": "^4.6.0",
    "cross-env": "^5.2.0",
    "eslint": "^5.8.0",
    "jquery": "^3.3.1",
    "uglifyjs-webpack-plugin": "^2.0.1",
    "webpack": "^4.20.2",
    "webpack-cli": "^3.1.2"
  }
}
